MANIFEST.in
README.rst
edgy.py
setup.py
edgy_json.egg-info/PKG-INFO
edgy_json.egg-info/SOURCES.txt
edgy_json.egg-info/dependency_links.txt
edgy_json.egg-info/top_level.txt