Metadata-Version: 1.1
Name: edgy-json
Version: 0.0.4
Summary: Verify JSON like a hipster.
Home-page: https://github.com/DXsmiley/edgy-json
Author: DXsmiley
Author-email: dxsmiley@hotmail.com
License: MIT
Keywords: validate verify json
Platform: UNKNOWN
Classifier: Development Status :: 3 - Alpha
Classifier: Intended Audience :: Developers
Classifier: License :: OSI Approved :: MIT License
Classifier: Programming Language :: Python :: 3
